aiozmq_heartbeat/__init__.py
aiozmq_heartbeat/publish.py
aiozmq_heartbeat/subscribe.py
aiozmq_heartbeat-0.0.1.dist-info/DESCRIPTION.rst
aiozmq_heartbeat-0.0.1.dist-info/METADATA
aiozmq_heartbeat-0.0.1.dist-info/RECORD
aiozmq_heartbeat-0.0.1.dist-info/WHEEL
aiozmq_heartbeat-0.0.1.dist-info/metadata.json
aiozmq_heartbeat-0.0.1.dist-info/top_level.txt
aiozmq_heartbeat-0.0.1.dist-info/zip-safe
