Metadata-Version: 2.0
Name: aiozmq-heartbeat
Version: 0.0.1
Summary: Simple heartbeat implementation on top of aiozmq.rpc
Home-page: https://github.com/akabos/aiozmq-heartbeat
Author: Mikhail Lukyanchenko
Author-email: ml@akabos.com
License: UNKNOWN
Platform: UNKNOWN
Classifier: Development Status :: 3 - Alpha
Classifier: Intended Audience :: Developers
Classifier: License :: OSI Approved :: BSD License
Classifier: Programming Language :: Python :: 3 :: Only
Classifier: Programming Language :: Python :: 3.5
Requires-Dist: aiozmq (>=0.7)
Requires-Dist: msgpack-python (>=0.4.6)
Requires-Dist: pyzmq (>=15.0.0)
